zencfg/__init__.py
zencfg/bunch.py
zencfg/config.py
zencfg/deprecated.py
zencfg/from_commandline.py
zencfg/from_dict.py
zencfg/from_file.py
zencfg/tests/__init__.py
zencfg/tests/test_autoconfig.py
zencfg/tests/test_bunch.py
zencfg/tests/test_config.py
zencfg/tests/test_deprecated.py
zencfg/tests/test_from_commandline.py
zencfg/tests/test_from_dict.py
zencfg/tests/test_from_file.py
zencfg/tests/test_parse.py
zencfg-0.6.0.dist-info/licenses/LICENSE
zencfg-0.6.0.dist-info/METADATA
zencfg-0.6.0.dist-info/WHEEL
zencfg-0.6.0.dist-info/top_level.txt
zencfg-0.6.0.dist-info/RECORD
