Metadata-Version: 2.4
Name: zencfg
Version: 0.6.0
Summary: The Zen way to configure your Python projects, deep learning and others
Author: Jean Kossaifi
License: MIT
Requires-Python: >=3.9
License-File: LICENSE
Requires-Dist: pydantic
Provides-Extra: doc
Requires-Dist: pytest; extra == "doc"
Requires-Dist: pytest-mock; extra == "doc"
Provides-Extra: all
Requires-Dist: pytest; extra == "all"
Requires-Dist: pytest-mock; extra == "all"
Requires-Dist: pydantic; extra == "all"
Dynamic: license-file
